AUTHORS
LICENSE
README.md
setup.py
loz/__init__.py
loz/__main__.py
loz/cry.py
loz/exceptions.py
loz/loz.py
loz.egg-info/PKG-INFO
loz.egg-info/SOURCES.txt
loz.egg-info/dependency_links.txt
loz.egg-info/entry_points.txt
loz.egg-info/requires.txt
loz.egg-info/top_level.txt